custom_logging/__about__.py
custom_logging/__init__.py
custom_logging/exceptions.py
custom_logging/filters.py
custom_logging/middlewares.py
custom_logging/utils.py
django_custom_logging-0.2.1.dist-info/METADATA
django_custom_logging-0.2.1.dist-info/WHEEL
django_custom_logging-0.2.1.dist-info/licenses/LICENSE
django_custom_logging-0.2.1.dist-info/RECORD
