Metadata-Version: 2.1
Name: django-custom-logging
Version: 0.2.1
Summary: Django middleware for custom format logging
Project-URL: Documentation, https://github.com/sh-cho/django-custom-logging#readme
Project-URL: Issues, https://github.com/sh-cho/django-custom-logging/issues
Project-URL: Source, https://github.com/sh-cho/django-custom-logging
Author-email: Seonghyeon Cho <seonghyeoncho96@gmail.com>
License-Expression: MIT
License-File: LICENSE
Keywords: django,logging,middleware
Classifier: Framework :: Django
Classifier: Intended Audience :: Developers
Classifier: License :: OSI Approved :: MIT License
Classifier: Operating System :: OS Independent
Classifier: Programming Language :: Python :: 3
Classifier: Programming Language :: Python :: 3 :: Only
Classifier: Programming Language :: Python :: 3.5
Classifier: Programming Language :: Python :: 3.6
Classifier: Programming Language :: Python :: 3.7
Classifier: Programming Language :: Python :: 3.8
Classifier: Programming Language :: Python :: 3.9
Classifier: Programming Language :: Python :: 3.10
Classifier: Programming Language :: Python :: 3.11
Classifier: Programming Language :: Python :: 3.12
Classifier: Programming Language :: Python :: Implementation :: PyPy
Classifier: Topic :: Software Development :: Libraries
Classifier: Topic :: Software Development :: Libraries :: Python Modules
Requires-Python: >=3.5
